README.md
setup.py
ml2en/__init__.py
ml2en/ml2en.py
ml2en.egg-info/PKG-INFO
ml2en.egg-info/SOURCES.txt
ml2en.egg-info/dependency_links.txt
ml2en.egg-info/top_level.txt