Metadata-Version: 2.1
Name: ml2en
Version: 1.0.0
Summary: A transliteration algorithm to transliterate Malayalam unicode strings to 'Manglish'
Home-page: https://github.com/knadh/ml2en
Author: Kailash Nadh
Author-email: kailash.nadh@gmail.com
License: GPLv2
Download-URL: https://github.com/knadh/ml2en
Platform: UNKNOWN
Classifier: Intended Audience :: Developers
Classifier: Programming Language :: Python
Classifier: Natural Language :: English
Classifier: License :: OSI Approved :: GNU General Public License v2 (GPLv2)
Classifier: Programming Language :: Python :: 2.6
Classifier: Programming Language :: Python :: 2.7
Classifier: Topic :: Software Development :: Libraries :: Python Modules
